tmux2html
