Metadata-Version: 1.1
Name: tmux2html
Version: 0.1.11
Summary: tmux2html captures full tmux windows or individual panes
Home-page: https://github.com/tweekmonster/tmux2html
Author: Tommy Allen
Author-email: tommy@esdf.io
License: MIT
Keywords: tmux html cool hip neat rad
Platform: UNKNOWN
Classifier: Development Status :: 4 - Beta
Classifier: Intended Audience :: Developers
Classifier: Intended Audience :: Information Technology
Classifier: Intended Audience :: System Administrators
Classifier: Topic :: Terminals :: Terminal Emulators/X Terminals
Classifier: Topic :: Utilities
Classifier: License :: OSI Approved :: MIT License
Classifier: Programming Language :: Python :: 2
Classifier: Programming Language :: Python :: 2.7
Classifier: Programming Language :: Python :: 3
Classifier: Programming Language :: Python :: 3.4
